openai_cost_calculator/__init__.py
openai_cost_calculator/core.py
openai_cost_calculator/estimate.py
openai_cost_calculator/parser.py
openai_cost_calculator/pricing.py
openai_cost_calculator/types.py
openai_cost_calculator-1.1.1.dist-info/licenses/LICENSE
openai_cost_calculator-1.1.1.dist-info/METADATA
openai_cost_calculator-1.1.1.dist-info/WHEEL
openai_cost_calculator-1.1.1.dist-info/top_level.txt
openai_cost_calculator-1.1.1.dist-info/RECORD
